cuetools/__init__.py
cuetools/models.py
cuetools/parser/__init__.py
cuetools/parser/errors.py
cuetools/parser/handlers.py
cuetools/parser/lex.py
cuetools/parser/parser.py
cuetools/parser/wrappers.py
cuetools/py.typed
cuetools/types/__init__.py
cuetools/types/frame_time.py
cuetools/types/lex.py
cuetools/types/syntax.py
cuetools/types/title_case.py
cuetools/types/validators.py
cuetools-1.1.0.dist-info/METADATA
cuetools-1.1.0.dist-info/WHEEL
cuetools-1.1.0.dist-info/licenses/LICENSE
cuetools-1.1.0.dist-info/RECORD
