Metadata-Version: 2.4
Name: cuetools
Version: 1.1.0
Summary: Lightweight CUE sheet toolkit for Python
License: MIT
License-File: LICENSE
Keywords: cue,audio,parser,metadata,cue-sheet
Author: Olezhich
Requires-Python: >=3.10
Classifier: License :: OSI Approved :: MIT License
Classifier: Programming Language :: Python :: 3
Classifier: Programming Language :: Python :: 3.10
Classifier: Programming Language :: Python :: 3.11
Classifier: Programming Language :: Python :: 3.12
Classifier: Programming Language :: Python :: 3.13
Classifier: Programming Language :: Python :: 3.14
Requires-Dist: pydantic (>=2.12.3,<3.0.0)
Project-URL: Changelog, https://github.com/Olezhich/CueTools/blob/main/CHANGELOG.md
Project-URL: Homepage, https://github.com/Olezhich/CueTools
Project-URL: Repository, https://github.com/Olezhich/CueTools
